README.md
setup.cfg
setup.py
yalies/__init__.py
yalies/main.py
yalies.egg-info/PKG-INFO
yalies.egg-info/SOURCES.txt
yalies.egg-info/dependency_links.txt
yalies.egg-info/requires.txt
yalies.egg-info/top_level.txt