Metadata-Version: 1.0
Name: yalies
Version: 1.1.0
Summary: Library for easy interaction with the Yalies API (yalies.io/apidocs)
Home-page: https://github.com/Yalies/yalies-python
Author: Erik Boesen
Author-email: me@erikboesen.com
License: MIT
Platform: UNKNOWN
